captcha_test/__init__.py
captcha_test/settings.py
captcha_test/urls.py
captcha_test/wsgi.py
captcha_varis_main-1.0.dist-info/METADATA
captcha_varis_main-1.0.dist-info/RECORD
captcha_varis_main-1.0.dist-info/WHEEL
captcha_varis_main-1.0.dist-info/top_level.txt
login/__init__.py
login/admin.py
login/apps.py
login/forms.py
login/image.py
login/models.py
login/tests.py
login/urls.py
login/views.py
login/migrations/__init__.py
